domain_equations/__init__.py
domain_equations/interface_generator.py
domain_equations/namedproperty.py
domain_equations/naming.py
domain_equations/property_graph.py
domain_equations/protobuf_generator.py
python_domain_equations-0.2.0.dist-info/LICENSE
python_domain_equations-0.2.0.dist-info/METADATA
python_domain_equations-0.2.0.dist-info/WHEEL
python_domain_equations-0.2.0.dist-info/top_level.txt
python_domain_equations-0.2.0.dist-info/RECORD
