Metadata-Version: 2.1
Name: python-domain-equations
Version: 0.2.0
Summary: python-domain-equations
Home-page: https://github.com/kummahiih/python-domain-equations
Author: Pauli Rikula
Author-email: UNKNOWN
License: MIT
Platform: UNKNOWN
Classifier: License :: OSI Approved :: MIT License
Classifier: Programming Language :: Python :: 3.6
Requires-Python: ~=3.6
Requires-Dist: python-category-equations (==0.7.2)
